README.md
setup.cfg
setup.py
bmlt_client/__init__.py
bmlt_client/api_client.py
bmlt_client/configuration.py
bmlt_client/exceptions.py
bmlt_client/rest.py
bmlt_client/schemas.py
bmlt_client/apis/__init__.py
bmlt_client/apis/path_to_api.py
bmlt_client/apis/tag_to_api.py
bmlt_client/apis/paths/__init__.py
bmlt_client/apis/paths/api_v1_auth_logout.py
bmlt_client/apis/paths/api_v1_auth_refresh.py
bmlt_client/apis/paths/api_v1_auth_token.py
bmlt_client/apis/paths/api_v1_formats.py
bmlt_client/apis/paths/api_v1_formats_format_id.py
bmlt_client/apis/paths/api_v1_meetings.py
bmlt_client/apis/paths/api_v1_meetings_meeting_id.py
bmlt_client/apis/paths/api_v1_servicebodies.py
bmlt_client/apis/paths/api_v1_servicebodies_service_body_id.py
bmlt_client/apis/paths/api_v1_users.py
bmlt_client/apis/paths/api_v1_users_user_id.py
bmlt_client/apis/tags/__init__.py
bmlt_client/apis/tags/root_server_api.py
bmlt_client/model/__init__.py
bmlt_client/model/authentication_error.py
bmlt_client/model/authorization_error.py
bmlt_client/model/format.py
bmlt_client/model/format_base.py
bmlt_client/model/format_collection.py
bmlt_client/model/format_create.py
bmlt_client/model/format_partial_update.py
bmlt_client/model/format_translation.py
bmlt_client/model/format_update.py
bmlt_client/model/meeting.py
bmlt_client/model/meeting_base.py
bmlt_client/model/meeting_collection.py
bmlt_client/model/meeting_create.py
bmlt_client/model/meeting_partial_update.py
bmlt_client/model/meeting_update.py
bmlt_client/model/not_found_error.py
bmlt_client/model/service_body.py
bmlt_client/model/service_body_base.py
bmlt_client/model/service_body_collection.py
bmlt_client/model/service_body_create.py
bmlt_client/model/service_body_partial_update.py
bmlt_client/model/service_body_update.py
bmlt_client/model/token.py
bmlt_client/model/token_credentials.py
bmlt_client/model/user.py
bmlt_client/model/user_base.py
bmlt_client/model/user_collection.py
bmlt_client/model/user_create.py
bmlt_root_server_client.egg-info/PKG-INFO
bmlt_root_server_client.egg-info/SOURCES.txt
bmlt_root_server_client.egg-info/dependency_links.txt
bmlt_root_server_client.egg-info/requires.txt
bmlt_root_server_client.egg-info/top_level.txt
